wampyre/__init__.py
wampyre/opcodes.py
wampyre/pattern.py
wampyre/realm.py
wampyre/session.py
wampyre/utils.py
wampyre/tests/__init__.py
wampyre/tests/test_pattern.py
wampyre/tests/test_session.py
wampyre/tests/test_utils.py
wampyre/transports/__init__.py
wampyre/transports/autowamp.py
wampyre/transports/base.py
wampyre/transports/django.py
wampyre-1.1.0.dist-info/METADATA
wampyre-1.1.0.dist-info/RECORD
wampyre-1.1.0.dist-info/WHEEL
wampyre-1.1.0.dist-info/top_level.txt
