Metadata-Version: 2.1
Name: wampyre
Version: 1.1.0
Summary: Python implementation of a WAMP router.
Home-page: https://github.com/JohnDoee/wampyre
Author: Anders Jensen
Author-email: johndoee@tidalstream.org
License: UNKNOWN
Platform: UNKNOWN
Classifier: Development Status :: 4 - Beta
Classifier: License :: OSI Approved :: MIT License
Classifier: Programming Language :: Python :: 3.6
Classifier: Programming Language :: Python :: 3.7
Provides-Extra: django
Provides-Extra: tests
Provides-Extra: django
Requires-Dist: channels; extra == 'django'
Requires-Dist: autobahn; extra == 'django'
Provides-Extra: tests
Requires-Dist: pytest; extra == 'tests'
